platonic/cached_property.py
platonic/const.py
platonic/mapping.py
platonic/queue/__init__.py
platonic/queue/base.py
platonic/queue/errors.py
platonic/queue/message.py
platonic/queue/receiver.py
platonic/queue/sender.py
platonic/queue/types.py
platonic/timeout/__init__.py
platonic/timeout/base.py
platonic/timeout/constant.py
platonic/timeout/infinite.py
platonic-1.2.1.dist-info/LICENSE
platonic-1.2.1.dist-info/WHEEL
platonic-1.2.1.dist-info/METADATA
platonic-1.2.1.dist-info/RECORD
