Metadata-Version: 2.1
Name: platonic
Version: 1.2.1
Summary: Abstract datastructures for Clean Architecture applications in Python.
Home-page: https://github.com/python-platonic/platonic
License: MIT
Requires-Python: >=3.7,<3.10
Classifier: Development Status :: 3 - Alpha
Classifier: Intended Audience :: Developers
Classifier: License :: OSI Approved :: MIT License
Classifier: Operating System :: OS Independent
Classifier: Programming Language :: Python :: 3
Classifier: Programming Language :: Python :: 3.7
Classifier: Programming Language :: Python :: 3.8
Classifier: Topic :: Software Development :: Libraries :: Python Modules
Requires-Dist: backports.cached-property (>=1.0.0,<2.0.0); python_version < "3.8"
Requires-Dist: typecasts (>=0.1.7,<0.2.0)
Project-URL: Repository, https://github.com/python-platonic/platonic
